config.toml
minispark/__init__.py
minispark/cli.py
minispark/minispark.py
minispark/connectors/base.py
minispark/connectors/csv_connector.py
minispark/connectors/duckdb_connector.py
minispark/connectors/excel_connector.py
minispark/connectors/json_connector.py
minispark/connectors/mysql_connector.py
minispark/connectors/sqlite_connector.py
minispark/engines/base.py
minispark/engines/duckdb_engine.py
minispark/engines/sqlite_engine.py
minispark/processors/data_processor.py
minispqrk-0.1.8.dist-info/METADATA
minispqrk-0.1.8.dist-info/WHEEL
minispqrk-0.1.8.dist-info/entry_points.txt
minispqrk-0.1.8.dist-info/top_level.txt
minispqrk-0.1.8.dist-info/RECORD
