Metadata-Version: 2.4
Name: minispqrk
Version: 0.1.8
Summary: 一个轻量级的Python库，用于从多种数据源读取数据并在本地进行高效处理，类似于Apache Spark的功能
Home-page: https://github.com/duanfu456/minispark
Author: 段福
Author-email: 段福 <duanfu456@163.cm>
License: MIT
Project-URL: Homepage, https://github.com/your-username/minispark
Project-URL: Repository, https://github.com/your-username/minispark
Project-URL: Documentation, https://github.com/your-username/minispark#readme
Keywords: spark,data-processing,pandas,sql,database
Classifier: Development Status :: 3 - Alpha
Classifier: Intended Audience :: Developers
Classifier: License :: OSI Approved :: MIT License
Classifier: Programming Language :: Python :: 3
Classifier: Programming Language :: Python :: 3.9
Classifier: Programming Language :: Python :: 3.10
Classifier: Programming Language :: Python :: 3.11
Classifier: Programming Language :: Python :: 3.12
Requires-Python: >=3.9
Requires-Dist: pandas>=1.3.0
Requires-Dist: sqlalchemy>=1.4.0
Requires-Dist: toml>=0.10.2
Requires-Dist: swifter>=1.0.0
Requires-Dist: loguru>=0.5.0
Provides-Extra: mysql
Requires-Dist: pymysql>=1.0.0; extra == "mysql"
Provides-Extra: duckdb
Requires-Dist: duckdb>=0.3.0; extra == "duckdb"
Provides-Extra: excel
Requires-Dist: openpyxl>=3.0.0; extra == "excel"
Requires-Dist: xlrd>=2.0.0; extra == "excel"
Dynamic: author
Dynamic: home-page
Dynamic: requires-python
